autotrend/__init__.py
autotrend/core/__init__.py
autotrend/core/decompose_llt_class.py
autotrend/core/functional_api.py
autotrend/core/llt_algorithm.py
autotrend/core/llt_result.py
autotrend/core/utility.py
autotrend/data/__init__.py
autotrend/data/sythn_data/__init__.py
autotrend/data/sythn_data/generate_nonstationary_wave.py
autotrend/data/sythn_data/generate_piecewise_linear.py
autotrend/data/sythn_data/generate_simple_wave.py
autotrend/decomposition/__init__.py
autotrend/visualization/__init__.py
autotrend/visualization/animate_error_threshold.py
autotrend/visualization/plot.py
autotrend/visualization/plot_error.py
autotrend/visualization/plot_full_decomposition.py
autotrend/visualization/plot_iteration_grid.py
autotrend/visualization/plot_model_statistics.py
autotrend/visualization/plot_slope.py
autotrend-0.2.4.dist-info/licenses/LICENSE
autotrend-0.2.4.dist-info/METADATA
autotrend-0.2.4.dist-info/WHEEL
autotrend-0.2.4.dist-info/top_level.txt
autotrend-0.2.4.dist-info/RECORD
