Metadata-Version: 2.4
Name: autotrend
Version: 0.2.4
Summary: Local Linear Trend Extraction for Time Series
Home-page: https://github.com/chotanansub/autotrend
Author: Chotanansub Sophaken
Author-email: Chotanansub Sophaken <chotanansub.s@gmail.com>
License: MIT
Project-URL: Homepage, https://github.com/chotanansub/autotrend
Project-URL: Documentation, https://github.com/chotanansub/autotrend#readme
Project-URL: Repository, https://github.com/chotanansub/autotrend
Project-URL: Bug Reports, https://github.com/chotanansub/autotrend/issues
Keywords: time-series,trend-extraction,linear-regression,segmentation,decomposition
Classifier: Development Status :: 3 - Alpha
Classifier: Intended Audience :: Developers
Classifier: Intended Audience :: Science/Research
Classifier: Topic :: Scientific/Engineering :: Information Analysis
Classifier: Topic :: Scientific/Engineering :: Mathematics
Classifier: License :: OSI Approved :: MIT License
Classifier: Programming Language :: Python :: 3
Classifier: Programming Language :: Python :: 3.8
Classifier: Programming Language :: Python :: 3.9
Classifier: Programming Language :: Python :: 3.10
Classifier: Programming Language :: Python :: 3.11
Requires-Python: >=3.8
License-File: LICENSE
Requires-Dist: numpy>=1.20.0
Requires-Dist: scikit-learn>=1.0.0
Requires-Dist: matplotlib>=3.3.0
Requires-Dist: seaborn>=0.11.0
Requires-Dist: scipy>=1.7.0
Provides-Extra: dev
Requires-Dist: pytest>=7.0.0; extra == "dev"
Requires-Dist: pytest-cov>=3.0.0; extra == "dev"
Requires-Dist: black>=22.0.0; extra == "dev"
Requires-Dist: flake8>=4.0.0; extra == "dev"
Requires-Dist: mypy>=0.950; extra == "dev"
Dynamic: author
Dynamic: home-page
Dynamic: license-file
Dynamic: requires-python
